yaml_plate/__init__.py
yaml_plate/emojipedia.py
yaml_plate/languages.py
yaml_plate/yaml_plate.py
YAML_Plate-1.0.3.dist-info/LICENSE
YAML_Plate-1.0.3.dist-info/METADATA
YAML_Plate-1.0.3.dist-info/WHEEL
YAML_Plate-1.0.3.dist-info/top_level.txt
YAML_Plate-1.0.3.dist-info/RECORD
