Metadata-Version: 2.1
Name: YAML-Plate
Version: 1.0.3
Summary: A fork of Plate (Internationalization library for Python), for YAML
Home-page: https://github.com/zakaryan2004/yaml_plate
Author: zakaryan2004
License: MIT
Project-URL: Tracker, https://github.com/zakaryan2004/yaml_plate/issues
Project-URL: Source, https://github.com/zakaryan2004/yaml_plate
Keywords: i18n internationalization l10n localization library python yaml interpolation pluralization emoji
Platform: UNKNOWN
Classifier: Development Status :: 5 - Production/Stable
Classifier: Intended Audience :: Developers
Classifier: License :: OSI Approved :: MIT License
Classifier: Operating System :: OS Independent
Classifier: Programming Language :: Python
Classifier: Programming Language :: Python :: 3
Classifier: Programming Language :: Python :: 3.5
Classifier: Programming Language :: Python :: 3.6
Classifier: Programming Language :: Python :: 3.7
Classifier: Programming Language :: Python :: 3.8
Classifier: Programming Language :: Python :: 3 :: Only
Classifier: Programming Language :: Python :: Implementation
Classifier: Programming Language :: Python :: Implementation :: CPython
Classifier: Programming Language :: Python :: Implementation :: PyPy
Classifier: Topic :: Software Development
Classifier: Topic :: Software Development :: Internationalization
Classifier: Topic :: Software Development :: Localization
Requires-Python: ~=3.5
Requires-Dist: PyYAML
